excel2meta_interface/__init__.py
excel2meta_interface/setup.py
excel2meta_interface/excel2json/__init__.py
excel2meta_interface/excel2json/excel2references.py
excel2meta_interface/excel2json/mapping_source_target_zones.py
excel2meta_interface/excel2json/reference2interface.py
excel2meta_interface/json2edc/__init__.py
excel2meta_interface/json2edc/create_1on1_metafiles_for_edc.py
excel2meta_interface/json2edc/create_metafiles_for_edc.py
excel2meta_interface/json2edc/json2edc_lineage_files.py
excel2meta_interface/json2edc/process_1on1_edc_lineage.py
excel2meta_interface/json2edc/upload_lineage_to_edc.py
excel2meta_interface/utils/__init__.py
excel2meta_interface/utils/check_schema.py
excel2meta_interface/utils/excel.py
excel2meta_interface/utils/helpers.py
excel2meta_interface/utils/messages.py
plugins/__init__.py
excel2meta_interface-0.1.35.dist-info/LICENSE
excel2meta_interface-0.1.35.dist-info/METADATA
excel2meta_interface-0.1.35.dist-info/WHEEL
excel2meta_interface-0.1.35.dist-info/top_level.txt
excel2meta_interface-0.1.35.dist-info/RECORD
